odoo/addons/purchase_delivery_split_date/README.rst
odoo/addons/purchase_delivery_split_date/__init__.py
odoo/addons/purchase_delivery_split_date/__manifest__.py
odoo/addons/purchase_delivery_split_date/i18n/ca.po
odoo/addons/purchase_delivery_split_date/i18n/de.po
odoo/addons/purchase_delivery_split_date/i18n/es.po
odoo/addons/purchase_delivery_split_date/i18n/es_MX.po
odoo/addons/purchase_delivery_split_date/i18n/es_PE.po
odoo/addons/purchase_delivery_split_date/i18n/fi.po
odoo/addons/purchase_delivery_split_date/i18n/fr.po
odoo/addons/purchase_delivery_split_date/i18n/gl.po
odoo/addons/purchase_delivery_split_date/i18n/hr.po
odoo/addons/purchase_delivery_split_date/i18n/it.po
odoo/addons/purchase_delivery_split_date/i18n/nl_NL.po
odoo/addons/purchase_delivery_split_date/i18n/pt_BR.po
odoo/addons/purchase_delivery_split_date/i18n/pt_PT.po
odoo/addons/purchase_delivery_split_date/i18n/purchase_delivery_split_date.pot
odoo/addons/purchase_delivery_split_date/i18n/ro.po
odoo/addons/purchase_delivery_split_date/i18n/sl.po
odoo/addons/purchase_delivery_split_date/i18n/zh_CN.po
odoo/addons/purchase_delivery_split_date/models/__init__.py
odoo/addons/purchase_delivery_split_date/models/purchase.py
odoo/addons/purchase_delivery_split_date/readme/CONTRIBUTORS.rst
odoo/addons/purchase_delivery_split_date/readme/DESCRIPTION.rst
odoo/addons/purchase_delivery_split_date/readme/HISTORY.rst
odoo/addons/purchase_delivery_split_date/readme/USAGE.rst
odoo/addons/purchase_delivery_split_date/static/description/icon.png
odoo/addons/purchase_delivery_split_date/static/description/index.html
odoo/addons/purchase_delivery_split_date/static/description/split_delivery.png
odoo/addons/purchase_delivery_split_date/tests/__init__.py
odoo/addons/purchase_delivery_split_date/tests/test_purchase_delivery.py
odoo13_addon_purchase_delivery_split_date-13.0.1.0.5.dist-info/METADATA
odoo13_addon_purchase_delivery_split_date-13.0.1.0.5.dist-info/WHEEL
odoo13_addon_purchase_delivery_split_date-13.0.1.0.5.dist-info/top_level.txt
odoo13_addon_purchase_delivery_split_date-13.0.1.0.5.dist-info/RECORD
