Metadata-Version: 2.1
Name: odoo13-addon-purchase-delivery-split-date
Version: 13.0.1.0.5
Summary: Allows Purchase Order you confirm to generate one Incoming Shipment for each expected date indicated in the Purchase Order Lines
Home-page: https://github.com/OCA/purchase-workflow
Author: Numerigraphe, ForgeFlow, Camptocamp, Odoo Community Association (OCA)
Author-email: support@odoo-community.org
License: AGPL-3
Platform: UNKNOWN
Classifier: Programming Language :: Python
Classifier: Framework :: Odoo
Classifier: License :: OSI Approved :: GNU Affero General Public License v3
Requires-Python: >=3.5
Requires-Dist: odoo (<13.1dev,>=13.0a)
